{
	"instance" : {
		"level:" : "",
		"serverName:" : "",
		"eventId" : "",
		"environment:" : "",
		"platform:" : "",
		"extra" : "",
		"asDictionary" : "",
		"logger:" : "",
		"sdk:" : "",
		"timestamp" : "",
		"initialize" : "",
		"eventId:" : "",
		"environment" : "",
		"platform" : "",
		"level" : "",
		"eventIdString" : "",
		"modules" : "",
		"uuid32For:" : "",
		"release:" : "",
		"message" : "",
		"contexts" : "",
		"timestamp:" : "",
		"fingerprint:" : "",
		"culprit" : "",
		"exception" : "",
		"requiredPayload" : "",
		"serverName" : "",
		"fingerprint" : "",
		"message:" : "",
		"modules:" : "",
		"culprit:" : "",
		"contexts:" : "",
		"extra:" : "",
		"sdk" : "",
		"tags" : "",
		"logger" : "",
		"isoTimestampFor:" : "",
		"release" : "",
		"exception:" : "",
		"tags:" : ""
	},
	"class" : { }
}